dora_pyaudio/__init__.py
dora_pyaudio/__main__.py
dora_pyaudio/main.py
dora_pyaudio-0.4.1.dist-info/METADATA
dora_pyaudio-0.4.1.dist-info/WHEEL
dora_pyaudio-0.4.1.dist-info/entry_points.txt
dora_pyaudio-0.4.1.dist-info/top_level.txt
dora_pyaudio-0.4.1.dist-info/RECORD
