Metadata-Version: 2.4
Name: dora-pyaudio
Version: 0.4.1
Summary: dora-pyaudio
Author-email: Haixuan Xavier Tao <tao.xavier@outlook.com>
License: MIT
Requires-Python: >=3.8
Requires-Dist: dora-rs>=0.3.9
Requires-Dist: numpy>=1.0.0
Requires-Dist: pyarrow>=5.0.0
Requires-Dist: pyaudio>=0.1.0
